datasette_sqlite_jiff/__init__.py
datasette_sqlite_jiff-0.0.1a2.dist-info/METADATA
datasette_sqlite_jiff-0.0.1a2.dist-info/WHEEL
datasette_sqlite_jiff-0.0.1a2.dist-info/entry_points.txt
datasette_sqlite_jiff-0.0.1a2.dist-info/top_level.txt
datasette_sqlite_jiff-0.0.1a2.dist-info/RECORD
